remove_quarantine/__init__.py
remove_quarantine/post_install.log
remove_quarantine-2023.2.0.dist-info/LICENSE.txt
remove_quarantine-2023.2.0.dist-info/METADATA
remove_quarantine-2023.2.0.dist-info/WHEEL
remove_quarantine-2023.2.0.dist-info/top_level.txt
remove_quarantine-2023.2.0.dist-info/RECORD
