Metadata-Version: 2.1
Name: remove_quarantine
Version: 2023.2.0
Summary: On install removes quarantine bit from Indigo Plugins
Author: GlennNZ
Author-email: GlennNZ <Try_Forum@IndigoDomo.com>
Maintainer-email: GlennNZ <See_Forum@Indigodomo.com>
License: MIT License
Project-URL: Homepage, https://github.com/Ghawken/remove_quarantine
Project-URL: Bug Reports, https://github.com/Ghawken/remove_quarantine
Project-URL: Funding, https://donate.pypi.org
Project-URL: Say Thanks!, https://github.com/Ghawken/remove_quarantine
Project-URL: Source, https://github.com/Ghawken/remove_quarantine
Classifier: Development Status :: 4 - Beta
Classifier: Intended Audience :: Developers
Classifier: Topic :: Software Development :: Build Tools
Classifier: Programming Language :: Python :: 3.11
Classifier: Programming Language :: Python :: 3 :: Only
Requires-Python: >=3.10
License-File: LICENSE.txt
